zookeeper_locks/__init__.py
zookeeper_locks/connection.py
zookeeper_locks/locks.py
zookeeper_locks/middleware.py
zookeeper_locks/test_runners.py
zookeeper_locks/management/__init__.py
zookeeper_locks/management/commands/__init__.py
zookeeper_locks/management/commands/migrate_with_zookeeper.py
zookeeper_locks/multiprocessing/__init__.py
zookeeper_locks/multiprocessing/hooks.py
zookeeper_locks/tests/__init__.py
zookeeper_locks/tests/test_commands.py
zookeeper_locks/tests/test_connection.py
zookeeper_locks/tests/test_lock.py
zookeeper_locks/tests/utils.py
django_zookeeper_locks-1.0.0.dist-info/LICENSE
django_zookeeper_locks-1.0.0.dist-info/METADATA
django_zookeeper_locks-1.0.0.dist-info/WHEEL
django_zookeeper_locks-1.0.0.dist-info/top_level.txt
django_zookeeper_locks-1.0.0.dist-info/RECORD
