Metadata-Version: 2.1
Name: django-zookeeper-locks
Version: 1.0.0
Summary: Utils for using Zookeeper locks through zookeeper in Django commands and views.
Author: WeDeploy
Author-email: github@wedeploy.com
Classifier: Environment :: Web Environment
Classifier: Framework :: Django
Classifier: Intended Audience :: Developers
Classifier: Operating System :: OS Independent
Classifier: Programming Language :: Python
Classifier: Programming Language :: Python :: 3.8
Classifier: Programming Language :: Python :: 3.9
Classifier: Programming Language :: Python :: 3.10
Classifier: Programming Language :: Python :: 3.11
License-File: LICENSE
Requires-Dist: Django (>=2.0)
Requires-Dist: kazoo (==2.8.0)
